segtraq/SegTraQ.py
segtraq/__init__.py
segtraq/utils.py
segtraq/bl/__init__.py
segtraq/bl/baseline.py
segtraq/bl/utils.py
segtraq/cs/__init__.py
segtraq/cs/clustering_stability.py
segtraq/cs/utils.py
segtraq/nc/__init__.py
segtraq/nc/nuclear_correlation.py
segtraq/nc/utils.py
segtraq/pl/__init__.py
segtraq/pl/plotting_functions.py
segtraq/ps/__init__.py
segtraq/ps/point_statistics.py
segtraq/sp/__init__.py
segtraq/sp/supervised.py
segtraq/vl/__init__.py
segtraq/vl/volume.py
segtraq-0.0.2.dist-info/licenses/LICENSE
segtraq-0.0.2.dist-info/METADATA
segtraq-0.0.2.dist-info/WHEEL
segtraq-0.0.2.dist-info/entry_points.txt
segtraq-0.0.2.dist-info/top_level.txt
segtraq-0.0.2.dist-info/RECORD
